logware
